offlix_installer/__init__.py
offlix_installer/banner.txt
offlix_installer/installer.py
test/__init__.py
test/test_main.py
offlix-0.1.5.2.dist-info/LICENSE
offlix-0.1.5.2.dist-info/METADATA
offlix-0.1.5.2.dist-info/WHEEL
offlix-0.1.5.2.dist-info/entry_points.txt
offlix-0.1.5.2.dist-info/top_level.txt
offlix-0.1.5.2.dist-info/RECORD
