Metadata-Version: 2.1
Name: offlix
Version: 0.1.5.2
Summary: Offlix is a command-line tool designed to simplify the deployment and management of common services using Docker Compose. With Offlix, you can easily install, uninstall, and retrieve environment variables for services like MySQL, MongoDB, Kafka, Maildev, and PostgreSQL, etc
Home-page: https://github.com/sumanmanna134/offlix-cli
Author: Suman Manna
Author-email: manna.suman134@gmail.com
Classifier: Programming Language :: Python :: 3
Classifier: License :: OSI Approved :: MIT License
Classifier: Operating System :: OS Independent
Requires-Python: >=3.6
License-File: LICENSE
Requires-Dist: docker
Requires-Dist: python-dotenv
